datalake/__init__.py
datalake/exceptions.py
datalake/helpers.py
datalake/interface.py
datalake/provider/aws.py
datalake/provider/azure.py
datalake/provider/gcp.py
datalake/provider/local.py
datalake/telemetry.py
datalake_framework-1.0.4.dist-info/LICENSE
datalake_framework-1.0.4.dist-info/WHEEL
datalake_framework-1.0.4.dist-info/METADATA
datalake_framework-1.0.4.dist-info/RECORD
